mkdocstrings_handlers/sequence/__init__.py
mkdocstrings_handlers/sequence/handler.py
mkdocstrings_handlers/sequence/templates/terminal/metadata.html
mkdocstrings_handlers/sequence/templates/terminal/ops.html
sequence/__init__.py
sequence/_version.py
sequence/cli.py
sequence/docs.py
sequence/static.py
sequence/utils.py
sequence/standard/__init__.py
sequence/standard/branching.py
sequence/standard/loops.py
sequence/standard/operators.py
sequence/standard/other.py
sequence/standard/stack_operations.py
sequence/standard/types.py
sequence/standard/resources/__init__.py
sequence/standard/resources/file.py
sequence/standard/resources/hson.py
sequence/standard/resources/json.py
sequence/standard/resources/json5.py
sequence/standard/resources/methods.py
sequence/standard/resources/variable.py
sequence/visitors/__init__.py
sequence/visitors/base.py
sequence/visitors/iterator.py
sequence/visitors/load.py
sequence/visitors/run.py
sequence/visitors/state.py
sequence/visitors/tester.py
sequence_stk-0.7.2.dist-info/LICENSE
sequence_stk-0.7.2.dist-info/METADATA
sequence_stk-0.7.2.dist-info/WHEEL
sequence_stk-0.7.2.dist-info/entry_points.txt
sequence_stk-0.7.2.dist-info/top_level.txt
sequence_stk-0.7.2.dist-info/RECORD
